log4jscanner/DNSCallBackProvider.py
log4jscanner/Log4jScanner.py
log4jscanner/__init__.py
log4jscanner/db/headers-large.txt
log4jscanner/db/headers-minimal.txt
log4jscanner/db/headers.txt
Log4jScanner-1.2.dist-info/LICENSE
Log4jScanner-1.2.dist-info/METADATA
Log4jScanner-1.2.dist-info/WHEEL
Log4jScanner-1.2.dist-info/entry_points.txt
Log4jScanner-1.2.dist-info/top_level.txt
Log4jScanner-1.2.dist-info/RECORD
