Metadata-Version: 2.1
Name: Log4jScanner
Version: 1.2
Summary: Log4j CVE Vulnerability Scanner - Python Module
Home-page: https://github.com/PushpenderIndia/Log4jScanner
Author: Pushpender Singh
Author-email: singhpushpender250@gmail.com
License: GNU General Public License v3 (GPLv3)
Keywords: log4jscanner,bug bounty,http,pentesting,security
Platform: UNKNOWN
Classifier: Development Status :: 5 - Production/Stable
Classifier: Intended Audience :: Developers
Classifier: Intended Audience :: Information Technology
Classifier: Operating System :: OS Independent
Classifier: Topic :: Security
Classifier: License :: OSI Approved :: GNU General Public License v3 (GPLv3)
Classifier: Programming Language :: Python :: 3
Classifier: Programming Language :: Python :: 3.4
Classifier: Programming Language :: Python :: 3.5
Classifier: Programming Language :: Python :: 3.6
Classifier: Programming Language :: Python :: 3.7
Classifier: Programming Language :: Python :: 3.8
Classifier: Programming Language :: Python :: 3.9
Requires-Dist: requests
Requires-Dist: PyCryptodome
Requires-Dist: colorama
Requires-Dist: pyfiglet
Requires-Dist: argparse
